pysequoia-0.1.29.dist-info/METADATA
pysequoia-0.1.29.dist-info/WHEEL
pysequoia-0.1.29.dist-info/licenses/LICENSE
pysequoia/__init__.py
pysequoia/pysequoia.cpython-312-aarch64-linux-gnu.so
pysequoia-0.1.29.dist-info/RECORD
