Metadata-Version: 2.4
Name: pysequoia
Version: 0.1.29
Classifier: License :: OSI Approved :: Apache Software License
Classifier: Development Status :: 4 - Beta
Classifier: Programming Language :: Rust
Classifier: Programming Language :: Python :: Implementation :: CPython
Classifier: Programming Language :: Python :: Implementation :: PyPy
Classifier: Topic :: Software Development :: Libraries
Classifier: Topic :: Software Development :: Libraries :: Python Modules
License-File: LICENSE
Summary: Provides OpenPGP facilities using Sequoia-PGP library
Keywords: openpgp,pgp,gpg,gnupg,sequoia
Home-Page: https://github.com/wiktor-k/pysequoia
Author-email: Wiktor Kwapisiewicz <wiktor@metacode.biz>
Requires-Python: >=3.7
Project-URL: homepage, https://github.com/wiktor-k/pysequoia
Project-URL: changelog, https://github.com/wiktor-k/pysequoia/tags
Project-URL: repository, https://github.com/wiktor-k/pysequoia
Project-URL: Bug Tracker, https://github.com/wiktor-k/pysequoia/issues
